pyeafe/__init__.py
pyeafe/assembly.py
pyeafe/utils.py
pyeafe-1.0.0.dist-info/LICENSE.txt
pyeafe-1.0.0.dist-info/METADATA
pyeafe-1.0.0.dist-info/WHEEL
pyeafe-1.0.0.dist-info/top_level.txt
pyeafe-1.0.0.dist-info/RECORD
