Metadata-Version: 2.1
Name: pyeafe
Version: 1.0.0
Summary: Edge-Averaged Finite Elements (EAFE) for FENiCS
Home-page: https://thepnpsolver.github.io
Author: The PNP Solver
Author-email: thepnpsolver@gmail.com
License: MIT License
Project-URL: Source Code, https://github.com/thepnpsolver/pyeafe
Platform: UNKNOWN
Requires-Dist: numpy (>=1.19.0)
Requires-Dist: petsc4py (>=3.12.0)
Requires-Dist: typing (>=3.7.4.3)
